supervise_api
