Metadata-Version: 1.1
Name: supervise-api
Version: 0.6.0
Summary: An API for running processes safely and securely
Home-page: https://github.com/catern/supervise
Author: catern
Author-email: sbaugh@catern.com
License: MIT
Keywords: linux subprocess processes
Platform: UNKNOWN
Classifier: License :: OSI Approved :: MIT License
Classifier: Operating System :: POSIX :: Linux
